deephaven_ui_datetimeinput/__init__.py
deephaven_ui_datetimeinput/deephaven_ui_datetimeinput_object.py
deephaven_ui_datetimeinput/deephaven_ui_datetimeinput_type.py
deephaven_ui_datetimeinput/js_plugin.py
deephaven_ui_datetimeinput/register.py
deephaven_ui_datetimeinput/_js/package.json
deephaven_ui_datetimeinput/_js/dist/index.js
deephaven_ui_datetimeinput-0.0.1.dev0.dist-info/LICENSE
deephaven_ui_datetimeinput-0.0.1.dev0.dist-info/METADATA
deephaven_ui_datetimeinput-0.0.1.dev0.dist-info/WHEEL
deephaven_ui_datetimeinput-0.0.1.dev0.dist-info/entry_points.txt
deephaven_ui_datetimeinput-0.0.1.dev0.dist-info/top_level.txt
deephaven_ui_datetimeinput-0.0.1.dev0.dist-info/RECORD
