Metadata-Version: 2.1
Name: deephaven_ui_datetimeinput
Version: 0.0.1.dev0
Summary: DateTime input plugin for Deephaven
Author: Deephaven Data Labs
Author-email: mikebender@deephaven.io
Keywords: deephaven,plugin,graph
Platform: any
License-File: LICENSE
Requires-Dist: deephaven-core >=0.31.0
Requires-Dist: deephaven-plugin >=0.6.0
Requires-Dist: deephaven-plugin-utilities
